fast_datacard/__init__.py
fast_datacard/cli.py
fast_datacard/dataframe_to_datacard_cfg.py
fast_datacard/io.py
fast_datacard/root_wrapper.py
fast_datacard-0.1.5.dist-info/AUTHORS.rst
fast_datacard-0.1.5.dist-info/LICENSE
fast_datacard-0.1.5.dist-info/METADATA
fast_datacard-0.1.5.dist-info/WHEEL
fast_datacard-0.1.5.dist-info/entry_points.txt
fast_datacard-0.1.5.dist-info/top_level.txt
fast_datacard-0.1.5.dist-info/RECORD
