Metadata-Version: 2.1
Name: fast-datacard
Version: 0.1.5
Summary: F.A.S.T. datacard creation package
Home-page: https://gitlab.cern.ch/fast-hep/public/fast-datacard
Author: F.A.S.T
Author-email: fast-hep@cern.ch
License: Apache Software License 2.0
Keywords: fast,datacard
Platform: UNKNOWN
Classifier: Development Status :: 2 - Pre-Alpha
Classifier: Intended Audience :: Developers
Classifier: License :: OSI Approved :: Apache Software License
Classifier: Natural Language :: English
Classifier: Programming Language :: Python :: 2
Classifier: Programming Language :: Python :: 2.7
Classifier: Programming Language :: Python :: 3
Classifier: Programming Language :: Python :: 3.4
Classifier: Programming Language :: Python :: 3.5
Classifier: Programming Language :: Python :: 3.6
Classifier: Programming Language :: Python :: 3.7
Requires-Dist: alphatwirl
Requires-Dist: Click (>=6.0)
Requires-Dist: jinja2
Requires-Dist: pandas
Requires-Dist: pyyaml
Requires-Dist: rootpy
Requires-Dist: root-numpy
